README.md
conan_build_tool/__init__.py
conan_build_tool.egg-info/PKG-INFO
conan_build_tool.egg-info/SOURCES.txt
conan_build_tool.egg-info/dependency_links.txt
conan_build_tool.egg-info/requires.txt
conan_build_tool.egg-info/top_level.txt
conan_build_tool/templates/execution_script.py