Metadata-Version: 2.1
Name: conan-build-tool
Version: 0.0.4
Summary: python script to automate package compilation of conan.io binary packages, full_version_string: 0.0.4-0-g47c1cfb
Home-page: https://github.com/Av3m/conan_build_tool
Author: Av3m
Author-email: av3m@openmailbox.org
License: UNKNOWN
Platform: UNKNOWN
Classifier: P
Classifier: r
Classifier: o
Classifier: g
Classifier: r
Classifier: a
Classifier: m
Classifier: m
Classifier: i
Classifier: n
Classifier: g
Classifier:  
Classifier: L
Classifier: a
Classifier: n
Classifier: g
Classifier: u
Classifier: a
Classifier: g
Classifier: e
Classifier:  
Classifier: :
Classifier: :
Classifier:  
Classifier: P
Classifier: y
Classifier: t
Classifier: h
Classifier: o
Classifier: n
Classifier:  
Classifier: :
Classifier: :
Classifier:  
Classifier: 3
